{
  "$schema": "https://json-schema.org/draft/2020-12/schema",
  "$id": "http://smart.who.int/trust-phw/StructureDefinition-PreQualVaccineDetails.schema.json",
  "title": "PreQual - Vaccine Details",
  "description": "Vaccine Data elements from the Pre Qual Database",
  "type": "object",
  "properties": {
    "productID": {
      "type": "object",
      "description": "Vaccine product information (note: use InventoryItem in FHIR R6)"
    },
    "date": {
      "type": "string",
      "format": "date",
      "description": "Date of vaccine"
    },
    "issuer": {
      "type": "object",
      "description": "Relevant authoring reponsible for issuing the certificate, or for overseeing the administration center"
    },
    "clinicianName": {
      "type": "string",
      "description": "Name of supervising clinician, or relevant authority responsible for issuing this certificate, or for overseeing the administering centre"
    },
    "batchNo": {
      "type": "object",
      "description": "Batch No"
    },
    "validityPeriod": {
      "type": "object",
      "description": "Certificate validity period"
    }
  },
  "required": [
    "productID",
    "date",
    "batchNo"
  ],
  "fhir:logicalModel": "http://smart.who.int/trust-phw/StructureDefinition/PreQualVaccineDetails",
  "fhir:parent": "http://smart.who.int/trust-phw/StructureDefinition/VaccineDetails"
}